aiteamutils/__init__.py
aiteamutils/base_model.py
aiteamutils/base_repository.py
aiteamutils/base_service.py
aiteamutils/cache.py
aiteamutils/config.py
aiteamutils/database.py
aiteamutils/enums.py
aiteamutils/exceptions.py
aiteamutils/files.py
aiteamutils/security.py
aiteamutils/validators.py
aiteamutils/version.py
aiteamutils-0.2.169.dist-info/METADATA
aiteamutils-0.2.169.dist-info/WHEEL
aiteamutils-0.2.169.dist-info/RECORD
