Metadata-Version: 2.4
Name: aiteamutils
Version: 0.2.169
Summary: AI Team Utilities
Project-URL: Homepage, https://github.com/yourusername/aiteamutils
Project-URL: Issues, https://github.com/yourusername/aiteamutils/issues
Author: AI Team
Classifier: License :: OSI Approved :: MIT License
Classifier: Operating System :: OS Independent
Classifier: Programming Language :: Python :: 3
Requires-Python: >=3.8
Requires-Dist: aiofiles
Requires-Dist: fastapi
Requires-Dist: python-jose
Requires-Dist: sqlalchemy
